fklib/__init__.py
fklib/functions.py
tests/__init__.py
tests/functions.py
fklib-0.0.1.dist-info/METADATA
fklib-0.0.1.dist-info/WHEEL
fklib-0.0.1.dist-info/top_level.txt
fklib-0.0.1.dist-info/RECORD
