Metadata-Version: 2.1
Name: fklib
Version: 0.0.1
Summary: Franektoube Library
Home-page: https://github.com/Franektoube/fklib
Author: Franektoube
Author-email: frankox7@interia.pl
License: UNKNOWN
Platform: UNKNOWN
Requires-Python: >=3.6
